PyCBD/__init__.py
PyCBD/logger_configuration.py
PyCBD/pipelines.py
PyCBD/checkerboard_detection/__init__.py
PyCBD/checkerboard_detection/checkerboard_detector.py
PyCBD/checkerboard_enhancement/__init__.py
PyCBD/checkerboard_enhancement/checkerboard_enhancer.py
pycbd-1.3.1.dist-info/licenses/LICENSE
pycbd-1.3.1.dist-info/METADATA
pycbd-1.3.1.dist-info/WHEEL
pycbd-1.3.1.dist-info/top_level.txt
pycbd-1.3.1.dist-info/RECORD
