Metadata-Version: 2.4
Name: PyCBD
Version: 1.3.1
Summary: PyCBD: Python Checkerboard Detection Toolbox
Author-email: Michaël Hillen <rhys.evans@uantwerpen.be>
Project-URL: Homepage, https://github.com/InViLabUAntwerp/PyCBD
Classifier: Programming Language :: Python :: 3
Classifier: License :: OSI Approved :: MIT License
Classifier: Operating System :: OS Independent
Requires-Python: >=3.10
License-File: LICENSE
Requires-Dist: numpy==1.26.4
Requires-Dist: matplotlib
Requires-Dist: scikit-learn
Requires-Dist: scipy
Requires-Dist: opencv-python
Requires-Dist: gpy
Requires-Dist: Pillow
Requires-Dist: h5py
Requires-Dist: albumentations
Requires-Dist: libCBDetect
Dynamic: license-file
